{
  "id": "fischer20140710a.pdf_9",
  "doc_id": "fischer20140710a.pdf",
  "content_type": "pdf",
  "page_dimension": " 0 0 1224 1584",
  "page_number": 9,
  "path": "/lots-of-files/fischer20140710a.pdf",
  "content": " - 8 -     that if the need arises, they will use macroprudential policies for that purpose.  By that   they mean policies that will reduce the supply of credit to the housing sector without   changing the central bank interest rate.   Sector-specific regulatory and supervisory policies in the financial sector were   used extensively and systematically in the United States in the period following World   War II until the 1990s and are now being used in other advanced and developing   countries.  Elliott, Feldberg, and Lehnert review the use of such measures in the United   States.10  Frequently, these policies were aimed at encouraging or discouraging activity in   particular sectors, for example agriculture, exports, manufacturing, or housing;   sometimes broad, non-interest-rate measures were used to try to deal with inflation or   asset-price increases, for instance, the use of credit controls.       The issue of how monetary policy should relate to asset-price inflation had been   on the agenda of central bankers for many years before the Lehman Brothers’ failure.11   The issue became more prominent in the United States in the 1990s and the first few   years of this century, and temporarily culminated in the Fed’s “mopping-up” approach,   namely that monetary policy--meaning interest rate policy--should not react to rising   asset prices or suspected bubbles except to the extent that they affect either employment   and/or price stability.  Operationally, this approach was much more likely to lead to   10 For a comprehensive review of the use of such policies, see Douglas J. Elliott, Greg Feldberg, and  Andreas Lehnert (2013), “The History of Cyclical Macroprudential Policy in the United States,” Finance  and Economics Discussion Series 2013-29 (Washington: Board of Governors of the Federal Reserve  System, May), www.federalreserve.gov/pubs/feds/2013/201329/201329abs.html.  11 Among the suggested solutions was the proposal that the consumer price index should include the prices  of assets as representing the costs of future consumption.  See Armen A. Alchian and Benjamin Klein  (1973), “On a Correct Measure of Inflation,” Journal of Money, Credit, and Banking, vol. 5 (1), part 1, pp.  173-91.       ",
  "content_ocr": "|OSA1ODkgODMgNjM1IDkz that|OSAxODEgMTQ5IDIxNiAxNjY= if|OSAyMjMgMTQ5IDIzOSAxNjY= the|OSAyNDMgMTQ5IDI3MSAxNjY= need|OSAyNzkgMTQ5IDMyMyAxNjY= arises,|OSAzMzAgMTQ5IDM4OSAxNjk= they|OSAzOTYgMTQ5IDQzNyAxNzE= will|OSA0NDQgMTQ5IDQ4MCAxNjY= use|OSA0ODcgMTU0IDUxOCAxNjY= macroprudential|OSA1MjUgMTQ5IDY4MSAxNzE= policies|OSA2ODggMTQ5IDc2MiAxNzE= for|OSA3NjkgMTQ5IDc5NyAxNjY= that|OSA4MDMgMTQ5IDgzOCAxNjY= purpose.|OSA4NDUgMTU0IDkyNSAxNzE= By|OSA5MzkgMTUwIDk2NiAxNzE= that|OSA5NzMgMTQ5IDEwMDggMTY2 they|OSAxODAgMjA0IDIyMSAyMjY= mean|OSAyMjggMjEwIDI3OSAyMjE= policies|OSAyODYgMjA0IDM1OSAyMjY= that|OSAzNjYgMjA0IDQwMSAyMjE= will|OSA0MDggMjA0IDQ0NCAyMjE= reduce|OSA0NTIgMjA0IDUxNSAyMjE= the|OSA1MjEgMjA0IDU1MCAyMjE= supply|OSA1NTcgMjA0IDYyMCAyMjY= of|OSA2MjcgMjA0IDY0OSAyMjE= credit|OSA2NTMgMjA0IDcwNyAyMjE= to|OSA3MTMgMjA3IDczMSAyMjE= the|OSA3MzggMjA0IDc2NyAyMjE= housing|OSA3NzQgMjA0IDg0OSAyMjY= sector|OSA4NTYgMjA3IDkxMiAyMjE= without|OSA5MTkgMjA0IDk5MSAyMjE= changing|OSAxODEgMjU5IDI2OCAyODE= the|OSAyNzQgMjU5IDMwMyAyNzY= central|OSAzMTAgMjU5IDM3MyAyNzY= bank|OSAzODEgMjU5IDQyNyAyNzY= interest|OSA0MzQgMjU5IDUwMyAyNzY= rate.|OSA1MTAgMjYyIDU1MCAyNzY= Sector-specific|OSAyNTMgMzE1IDM5NSAzMzY= regulatory|OSA0MDIgMzE1IDUwMCAzMzY= and|OSA1MDcgMzE1IDU0MSAzMzI= supervisory|OSA1NDggMzE0IDY1OSAzMzY= policies|OSA2NjUgMzE0IDczOSAzMzY= in|OSA3NDcgMzE0IDc2NCAzMzE= the|OSA3NzEgMzE1IDc5OSAzMzI= financial|OSA4MDcgMzE1IDg4OCAzMzI= sector|OSA4OTcgMzE3IDk1MyAzMzI= were|OSA5NjAgMzIwIDEwMDUgMzMy used|OSAxODEgMzcwIDIyNCAzODc= extensively|OSAyMzEgMzcwIDMzOSAzOTI= and|OSAzNDYgMzcwIDM3OSAzODc= systematically|OSAzODcgMzcwIDUyMyAzOTI= in|OSA1MzAgMzcwIDU0NiAzODY= the|OSA1NTQgMzcwIDU4MiAzODc= United|OSA1OTAgMzcwIDY1NCAzODc= States|OSA2NjIgMzcwIDcxNyAzODc= in|OSA3MjUgMzcwIDc0MiAzODY= the|OSA3NDkgMzcwIDc3NyAzODc= period|OSA3ODQgMzcwIDg0NSAzOTI= following|OSA4NTMgMzcwIDk0NCAzOTI= World|OSA5NTEgMzcwIDEwMTIgMzg3 War|OSAxODEgNDI2IDIyMSA0NDI= II|OSAyMjggNDI2IDI0MyA0NDI= until|OSAyNTAgNDI1IDI5MiA0NDI= the|OSAzMDAgNDI1IDMyOCA0NDI= 1990s|OSAzMzggNDI1IDM5MSA0NDI= and|OSAzOTkgNDI1IDQzMiA0NDI= are|OSA0NDAgNDMwIDQ2NyA0NDI= now|OSA0NzQgNDMwIDUxNSA0NDI= being|OSA1MjEgNDI1IDU3NCA0NDc= used|OSA1ODEgNDI1IDYyNCA0NDI= in|OSA2MzIgNDI1IDY0OSA0NDI= other|OSA2NTYgNDI1IDcwNSA0NDI= advanced|OSA3MTEgNDI1IDgwMSA0NDI= and|OSA4MDggNDI1IDg0MSA0NDI= developing|OSA4NDggNDI1IDk1NCA0NDc= countries.|OSAxODEgNDgwIDI3MiA0OTc= Elliott,|OSAyODcgNDgwIDM1MSA1MDA= Feldberg,|OSAzNTkgNDgwIDQ0OCA1MDI= and|OSA0NTYgNDgwIDQ4OSA0OTc= Lehnert|OSA0OTcgNDgwIDU3MCA0OTc= review|OSA1NzcgNDgwIDY0MSA0OTc= the|OSA2NDggNDgwIDY3NyA0OTc= use|OSA2ODQgNDg2IDcxNSA0OTc= of|OSA3MjIgNDgwIDc0NCA0OTc= such|OSA3NDggNDgwIDc5MCA0OTc= measures|OSA3OTggNDg2IDg4NiA0OTc= in|OSA4OTQgNDgwIDkxMSA0OTc= the|OSA5MTggNDgwIDk0NiA0OTc= United|OSA5NTQgNDgwIDEwMTcgNDk3 States.!°|OSAxODEgNTMyIDI2MCA1NTI= Frequently,|OSAyNzMgNTM1IDM4MSA1NTc= these|OSAzODkgNTM1IDQzNyA1NTI= policies|OSA0NDQgNTM1IDUxOCA1NTc= were|OSA1MjUgNTQxIDU3MCA1NTI= aimed|OSA1NzggNTM1IDYzNSA1NTI= at|OSA2NDMgNTM4IDY1OSA1NTI= encouraging|OSA2NjYgNTM1IDc4MyA1NTc= or|OSA3OTAgNTQxIDgxMCA1NTI= discouraging|OSA4MTYgNTM1IDkzOSA1NTc= activity|OSA5NDYgNTM1IDEwMTggNTU3 in|OSAxMDI1IDUzNSAxMDQyIDU1Mg== particular|OSAxODAgNTkwIDI3MiA2MTI= sectors,|OSAyNzkgNTk0IDM0OSA2MTE= for|OSAzNTggNTkxIDM4NSA2MDg= example|OSAzOTEgNTkwIDQ3MSA2MTI= agriculture,|OSA0NzkgNTkwIDU4NiA2MTI= exports,|OSA1OTUgNTk0IDY2OSA2MTI= manufacturing,|OSA2NzcgNTkxIDgyMSA2MTI= or|OSA4MjkgNTk2IDg0OCA2MDg= housing;|OSA4NTUgNTkwIDkzNSA2MTI= sometimes|OSAxODEgNjQ2IDI4MiA2NjM= broad,|OSAyOTAgNjQ2IDM0OCA2NjY= non-interest-rate|OSAzNTYgNjQ2IDUxMyA2NjM= measures|OSA1MjAgNjUxIDYwOCA2NjM= were|OSA2MTYgNjUxIDY2MSA2NjM= used|OSA2NjkgNjQ2IDcxMSA2NjM= to|OSA3MTggNjQ5IDczNiA2NjM= try|OSA3NDMgNjQ5IDc2OCA2Njg= to|OSA3NzUgNjQ4IDc5MyA2NjM= deal|OSA4MDAgNjQ2IDgzOCA2NjM= with|OSA4NDYgNjQ2IDg4NyA2NjM= inflation|OSA4OTUgNjQ2IDk3NCA2NjM= or|OSA5ODIgNjUxIDEwMDIgNjYz asset-price|OSAxODEgNzAxIDI4MiA3MjM= increases,|OSAyOTAgNzAxIDM4MSA3MjE= for|OSAzODkgNzAxIDQxNyA3MTg= instance,|OSA0MjQgNzAxIDUwNiA3MjE= the|OSA1MTQgNzAxIDU0MiA3MTg= use|OSA1NDkgNzA2IDU4MCA3MTg= of|OSA1ODcgNzAxIDYwOSA3MTg= credit|OSA2MTMgNzAxIDY2NyA3MTg= controls.|OSA2NzQgNzAxIDc1NSA3MTg= The|OSAyNTMgNzU2IDI4OSA3NzM= issue|OSAyOTcgNzU2IDM0MyA3NzM= of|OSAzNTAgNzU2IDM3MiA3NzM= how|OSAzNzYgNzU2IDQxNiA3NzM= monetary|OSA0MjMgNzU5IDUxMyA3Nzg= policy|OSA1MTkgNzU2IDU3OSA3Nzg= should|OSA1ODYgNzU2IDY0OSA3NzM= relate|OSA2NTYgNzU2IDcwOCA3NzM= to|OSA3MTUgNzU5IDczMiA3NzM= asset-price|OSA3NDAgNzU2IDg0MSA3Nzg= inflation|OSA4NDkgNzU2IDkyOCA3NzM= had|OSA5MzYgNzU2IDk2OSA3NzM= been|OSA5NzYgNzU2IDEwMjAgNzcz on|OSAxODEgODE3IDIwNCA4Mjg= the|OSAyMTEgODExIDIzOSA4Mjg= agenda|OSAyNDYgODExIDMxMyA4MzM= of|OSAzMjAgODExIDM0MiA4Mjg= central|OSAzNDYgODExIDQwOSA4Mjg= bankers|OSA0MTcgODExIDQ5MCA4Mjg= for|OSA0OTggODExIDUyNSA4Mjg= many|OSA1MzIgODE3IDU4NSA4MzM= years|OSA1OTEgODE3IDY0MCA4MzM= before|OSA2NDcgODExIDcwOCA4Mjg= the|OSA3MTUgODExIDc0MyA4Mjg= Lehman|OSA3NTEgODExIDgyOCA4Mjg= Brothers’|OSA4MzUgODExIDkyMyA4Mjg= failure.|OSA5MzIgODExIDk5OCA4Mjg= !!|OSAxMDA0IDgwOCAxMDE0IDgxOQ== The|OSAxODEgODY3IDIxNyA4ODQ= issue|OSAyMjQgODY3IDI3MSA4ODQ= became|OSAyNzggODY2IDM1MCA4ODQ= more|OSAzNTcgODcyIDQwNSA4ODQ= prominent|OSA0MTIgODY3IDUxMCA4ODg= in|OSA1MTggODY3IDUzNCA4ODM= the|OSA1NDIgODY3IDU3MCA4ODQ= United|OSA1NzcgODY2IDY0MSA4ODQ= States|OSA2NDkgODY3IDcwNCA4ODQ= in|OSA3MTIgODY2IDcyOSA4ODM= the|OSA3MzcgODY3IDc2NSA4ODQ= 1990s|OSA3NzQgODY3IDgyOCA4ODQ= and|OSA4MzUgODY3IDg2OSA4ODQ= the|OSA4NzYgODY3IDkwNCA4ODQ= first|OSA5MTIgODY3IDk0OSA4ODQ= few|OSA5NTYgODY3IDk5MCA4ODQ= years|OSAxODEgOTI3IDIzMCA5NDQ= of|OSAyMzcgOTIyIDI1NSA5Mzk= this|OSAyNjMgOTIyIDI5NiA5Mzk= century,|OSAzMDQgOTI1IDM4MCA5NDQ= and|OSAzODggOTIyIDQyMSA5Mzk= temporarily|OSA0MjggOTIyIDUzOSA5NDQ= culminated|OSA1NDcgOTIyIDY1MiA5Mzk= in|OSA2NTkgOTIyIDY3NiA5Mzg= the|OSA2ODQgOTIyIDcxMiA5Mzk= Fed’s|OSA3MTkgOTIyIDc3MSA5Mzk= “mopping-up”|OSA3NzkgOTIyIDkxNiA5NDQ= approach,|OSA5MjMgOTIyIDEwMTUgOTQ0 namely|OSAxODEgOTc3IDI1MCA5OTk= that|OSAyNTcgOTc3IDI5MiA5OTQ= monetary|OSAyOTkgOTgwIDM4OSA5OTk= policy--meaning|OSAzOTUgOTc3IDU1MyA5OTk= interest|OSA1NjEgOTc3IDYzMCA5OTQ= rate|OSA2MzcgOTgwIDY3MiA5OTQ= policy--should|OSA2NzkgOTc3IDgxOCA5OTk= not|OSA4MjUgOTgwIDg1NSA5OTQ= react|OSA4NjIgOTgwIDkwNyA5OTQ= to|OSA5MTQgOTgwIDkzMiA5OTQ= rising|OSA5MzkgOTc3IDk5MyA5OTk= asset|OSAxODEgMTAzNSAyMjYgMTA0OQ== prices|OSAyMzMgMTAzMiAyODkgMTA1NA== or|OSAyOTYgMTAzOCAzMTYgMTA0OQ== suspected|OSAzMjMgMTAzMiA0MTUgMTA1NA== bubbles|OSA0MjEgMTAzMiA0OTUgMTA0OQ== except|OSA1MDMgMTAzNSA1NjQgMTA1NA== to|OSA1NzEgMTAzNSA1ODggMTA0OQ== the|OSA1OTYgMTAzMiA2MjQgMTA0OQ== extent|OSA2MzEgMTAzNSA2ODkgMTA0OQ== that|OSA2OTUgMTAzMiA3MzEgMTA0OQ== they|OSA3MzcgMTAzMiA3NzggMTA1NA== affect|OSA3ODUgMTAzMiA4MzggMTA0OQ== either|OSA4NDYgMTAzMiA5MDAgMTA0OQ== employment|OSA5MDcgMTAzMiAxMDI1IDEwNTQ= and/or|OSAxODEgMTA4NyAyNDEgMTEwNA== price|OSAyNDggMTA4NyAyOTQgMTEwOQ== stability.|OSAzMDIgMTA4NyAzODMgMTEwOQ== Operationally,|OSAzOTcgMTA4NyA1MzMgMTEwOQ== this|OSA1NDEgMTA4NyA1NzQgMTEwNA== approach|OSA1ODIgMTA4NyA2NjkgMTEwOQ== was|OSA2NzYgMTA5MyA3MTIgMTEwNA== much|OSA3MTkgMTA4NyA3NzEgMTEwNA== more|OSA3NzggMTA5MyA4MjYgMTEwNA== likely|OSA4MzQgMTA4NyA4ODggMTEwOQ== to|OSA4OTQgMTA5MCA5MTIgMTEwNA== lead|OSA5MjAgMTA4NyA5NTggMTEwNA== to|OSA5NjUgMTA5MCA5ODMgMTEwNA== 10|OSAxODIgMTIzNSAxOTMgMTI0NA== For|OSAxOTkgMTIzOCAyMjYgMTI1MQ== a|OSAyMzIgMTI0MiAyMzkgMTI1MQ== comprehensive|OSAyNDUgMTIzNyAzNjUgMTI1NQ== review|OSAzNzIgMTIzNyA0MjUgMTI1MQ== of|OSA0MjAgMTIyNyA0MzkgMTI1OQ== the|OSA0NDEgMTIzNyA0NzUgMTI1MQ== use|OSA0ODIgMTI0MiA1MDcgMTI1MQ== of|OSA1MDggMTIyNyA1MjIgMTI1OQ== such|OSA1MjQgMTIzNyA1NzAgMTI1MQ== policies,|OSA1NzcgMTIzNyA2NDIgMTI1NQ== see|OSA2NDkgMTI0MiA2NzMgMTI1MQ== Douglas|OSA2ODAgMTIzNyA3NDUgMTI1NQ== J.|OSA3NTEgMTIzOCA3NjIgMTI1MQ== Elliott,|OSA3NzAgMTIzNyA4MjIgMTI1NA== Greg|OSA4MjkgMTIzOCA4NjggMTI1NQ== Feldberg,|OSA4NzUgMTIzNyA5NDggMTI1NQ== and|OSA5NTUgMTIzNyA5ODMgMTI1MQ== Andreas|OSAxODEgMTI2MCAyNDYgMTI3NA== Lehnert|OSAyNTMgMTI2MCAzMTMgMTI3NA== (2013),|OSAzMTkgMTI2MCAzNzYgMTI3Nw== “The|OSAzODMgMTI2MCA0MjIgMTI3NA== History|OSA0MjggMTI2MSA0ODcgMTI3OA== of|OSA0OTMgMTI2MCA1MTEgMTI3NA== Cyclical|OSA1MTQgMTI2MCA1NzkgMTI3OA== Macroprudential|OSA1ODcgMTI2MCA3MTggMTI3OA== Policy|OSA3MjUgMTI2MCA3NzUgMTI3OA== in|OSA3ODEgMTI2MCA3OTUgMTI3NA== the|OSA4MDEgMTI2MCA4MjQgMTI3NA== United|OSA4MzEgMTI2MCA4ODMgMTI3NA== States,”|OSA4OTAgMTI2MCA5NTAgMTI3Nw== Finance|OSA5NTcgMTI2MCAxMDE5IDEyNzQ= and|OSAxODEgMTI4MyAyMDggMTI5Nw== Economics|OSAyMTUgMTI4MyAzMDIgMTI5Nw== Discussion|OSAzMDggMTI4MyAzOTUgMTI5Nw== Series|OSA0MDIgMTI4MyA0NDkgMTI5Nw== 2013-29|OSA0NTUgMTI4MyA1MjAgMTI5Nw== (Washington:|OSA1MjcgMTI4MyA2MzMgMTMwMQ== Board|OSA2NDAgMTI4MyA2ODggMTI5Nw== of|OSA2OTUgMTI4MyA3MTMgMTI5Nw== Governors|OSA3MTYgMTI4MyA3OTkgMTI5Nw== of|OSA3OTUgMTI3OSA4MjEgMTMwNg== the|OSA4MjcgMTI4MyA4NTAgMTI5Nw== Federal|OSA4NTcgMTI4MyA5MTUgMTI5Nw== Reserve|OSA5MjIgMTI4NCA5ODUgMTI5Nw== System,|OSAxODEgMTMwNiAyNDMgMTMyNA== May),|OSAyNTAgMTMwNyAyOTYgMTMyNA== www.|OSAzMDMgMTMxMSAzNDUgMTMyMA== e.gov/pubs/feds/2013/201329/201329abs.html|OSA0NTYgMTMwNiA4MjQgMTMyMg== '!|OSAxODIgMTMyNyAxOTEgMTMzNg== Among|OSAxOTkgMTMzMCAyNTcgMTM0Nw== the|OSAyNjQgMTMyOSAyODggMTM0Mw== suggested|OSAyOTQgMTMyOSAzNzIgMTM0Nw== solutions|OSAzNzggMTMyOSA0NDkgMTM0Mw== was|OSA0NTUgMTMzNCA0ODUgMTM0Mw== the|OSA0OTEgMTMyOSA1MTQgMTM0Mw== proposal|OSA1MjIgMTMyOSA1ODkgMTM0Nw== that|OSA1OTUgMTMyOSA2MjQgMTM0Mw== the|OSA2MzAgMTMyOSA2NTQgMTM0Mw== consumer|OSA2NjAgMTMzNCA3MzcgMTM0Mw== price|OSA3NDMgMTMyOSA3ODEgMTM0Nw== index|OSA3ODggMTMyOSA4MzEgMTM0Mw== should|OSA4MzcgMTMyOSA4ODkgMTM0Mw== include|OSA4OTYgMTMyOSA5NTMgMTM0Mw== the|OSA5NTkgMTMyOSA5ODIgMTM0Mw== prices|OSA5ODkgMTMyOSAxMDM1IDEzNDc= of|OSAxNzAgMTM0OCAxODkgMTM3NA== assets|OSAxOTEgMTM1MiAyNDggMTM2Ng== as|OSAyNTQgMTM1NyAyNjkgMTM2Ng== representing|OSAyNzYgMTM1MiAzNzMgMTM3MA== the|OSAzNzkgMTM1MiA0MDIgMTM2Ng== costs|OSA0MDkgMTM1NSA0NDggMTM2Ng== of|OSA0NTQgMTM1MiA0NzIgMTM2Ng== future|OSA0NzYgMTM1MiA1MjIgMTM2Ng== consumption.|OSA1MjggMTM1MiA2MzQgMTM3MA== See|OSA2NDcgMTM1MyA2NzQgMTM2Ng== Armen|OSA2ODEgMTM1MyA3MzQgMTM2Ng== A.|OSA3NDEgMTM1MyA3NTggMTM2Ng== Alchian|OSA3NjYgMTM1MiA4MjcgMTM2Ng== and|OSA4MzQgMTM1MiA4NjEgMTM2Ng== Benjamin|OSA4NjggMTM1MiA5NDQgMTM3MA== Klein|OSA5NTEgMTM1MiA5OTMgMTM2Ng== (1973),|OSAxODEgMTM3NiAyMzggMTM5Mw== “On|OSAyNDQgMTM3NiAyNzYgMTM4OQ== a|OSAyODIgMTM4MCAyOTAgMTM4OQ== Correct|OSAyOTYgMTM3NiAzNTUgMTM4OQ== Measure|OSAzNjEgMTM3NiA0MjkgMTM4OQ== of|OSA0MjUgMTM2NiA0NDQgMTM5OA== Inflation,”|OSA0NDUgMTM3NSA1MzggMTM5Mg== Journal|OSA1NDMgMTM3NSA2MDYgMTM4OQ== of|OSA2MTIgMTM3NSA2MzEgMTM5Mw== Money,|OSA2MzIgMTM3NSA2ODkgMTM5Mw== Credit,|OSA2OTggMTM3NSA3NTAgMTM5MQ== and|OSA3NTggMTM3NSA3ODggMTM4OQ== Banking,|OSA3OTMgMTM3NSA4NjMgMTM5Mw== vol.|OSA4NzAgMTM3NSA4OTggMTM4OQ== 5|OSA5MDYgMTM3NiA5MTMgMTM4OQ== (1),|OSA5MjAgMTM3NiA5NDcgMTM5Mw== part|OSA5NTQgMTM3OCA5ODQgMTM5Mw== 1,|OSA5OTMgMTM3NiAxMDAzIDEzOTI= pp.|OSAxMDEwIDEzODAgMTAzMyAxMzkz 173-91.|OSAxODMgMTM5OCAyNDAgMTQxMg== ",
  "document_type": null
}
