{
  "id": "powell20180508a.pdf_17",
  "doc_id": "powell20180508a.pdf",
  "content_type": "pdf",
  "page_dimension": " 0 0 1440 1080",
  "page_number": 17,
  "path": "/lots-of-files/powell20180508a.pdf",
  "content": " Bord of Governors of the Federal Reserve System May 8, 2018                                 Board of Governors of the Federal Reserve System                                 7  Figure 7: Emerging market corporate debt at risk has begun to  reverse its earlier rise, even in China ",
  "content_ocr": "Figure|MTcgMTE1IDg2IDIzMyAxMjY= 7:|MTcgMjQ3IDg3IDI4MCAxMTg= Emerging|MTcgMjk3IDg2IDQ3OSAxMjY= market|MTcgNDk0IDg1IDYzMSAxMTg= corporate|MTcgNjQ1IDg5IDgzNSAxMjY= debt|MTcgODUwIDg1IDkzOSAxMTg= at|MTcgOTUzIDg5IDk5MCAxMTg= risk|MTcgMTAwNSA4NSAxMDcyIDExOA== has|MTcgMTA4NiA4NSAxMTUxIDExOA== begun|MTcgMTE2NiA4NSAxMjg1IDEyNg== to|MTcgMTI5OCA4OSAxMzM5IDExOA== reverse|MTcgMzY5IDE1MiA1MTEgMTc2 its|MTcgNTI2IDE0MyA1NzAgMTc2 earlier|MTcgNTg0IDE0MiA3MTEgMTc2 rise,|MTcgNzI1IDE0MyA4MDUgMTgy even|MTcgODIwIDE1MiA5MTEgMTc2 in|MTcgOTI4IDE0MyA5NjAgMTc1 China|MTcgOTc1IDE0MiAxMDgzIDE3Ng== |MTcgMTQ1IDIxMSAxMzIwIDIyMw== Percent|MTcgMTAyOCAyNjcgMTA4NSAyODA= of|MTcgMTA4OSAyNjcgMTEwNCAyODA= GDP|MTcgMTEwOCAyNjcgMTE0MyAyODA= 70|MTcgMTE1NSAyODAgMTE3MiAyOTI= 4-quarter|MTcgMjYxIDMwMSAzMjkgMzE2 moving|MTcgMzM0IDMwMyAzODYgMzE2 average|MTcgMzkyIDMwMyA0NTEgMzE2 |MTcgODUxIDMyMyAxMDM4IDQ2NQ== |MTcgODUxIDQ2NSAxMTM5IDUyNQ== |MTcgNzI2IDUyNSAxMTM5IDYyMA== |MTcgMjQwIDYyMCA5NDIgNzAx |MTcgMjQwIDcwMSA3NDIgNzU5 Asian|MTcgNjU4IDQ0NyA2OTkgNDU5 financial|MTcgNzA0IDQ0NyA3NjQgNDU5 crisis**|MTcgNzcwIDQ0NyA4MjAgNDU5 r|MTcgMjM1IDUxMSAyNDIgNTEz China|MTcgNzc1IDUwNyA4MTkgNTE5 2017:Q3|MTcgMTA3NCA2MDEgMTEzNyA2MTQ= |MTcgMjMxIDI4OCAyMzcgODEy |MTcgMTE0MiAyODggMTE0OCA4MTI= |MTcgMjMzIDgwOCAxMTQ2IDgxNQ== ~~|MTcgMjQ4IDY1MyAyODcgNjk2 420|MTcgMTEzOCA2NTUgMTE3MiA2Njc= .|MTcgMzA0IDY5OCAzMDYgNzAw EME|MTcgODQyIDY4MiA4NzcgNjk1 ex.|MTcgODgyIDY4NSA5MDQgNjk1 China|MTcgOTExIDY4MiA5NTUgNjk1 L.|MTcgMjIzIDcxNyAyNDIgNzQ3 eee|MTcgNjg5IDczMyA3NzggNzQ3 SSL|MTcgMTA3OSA3MTkgMTEyNyA3NDE= 440|MTcgMTEzOCA3MTUgMTE3MSA3NDc= poautori|MTcgMjUzIDc5NyAzODMgODEx tipi|MTcgNDAyIDc5NyA0NjggODEx tera|MTcgNDg3IDc5NyA1NTMgODEx tipi|MTcgNTcyIDc5NyA2MzcgODEx tira|MTcgNjU3IDc5NyA3MjIgODEx tiritipvitiritiiitiitg|MTcgNzQyIDc5NyAxMTYzIDgxNw== 2007|MTcgMjU4IDgyMCAyOTQgODMz 2008|MTcgMzM0IDgxNiAzNzkgODQy 2009|MTcgNDE5IDgxNiA0NjYgODQy 2010|MTcgNTEyIDgyMCA1NDggODMz 2011|MTcgNTg4IDgxNiA2MzEgODQy 2012|MTcgNjczIDgxNiA3MTggODQy 2013|MTcgNzU4IDgxNiA4MDMgODQy 2014|MTcgODQzIDgxNiA4ODggODQy 2015|MTcgOTM2IDgyMCA5NzIgODMz 2016|MTcgMTAxMiA4MTYgMTA1NyA4NDI= 2017|MTcgMTEwNiA4MjAgMTE0MiA4MzM= Note:|MTcgMjQ5IDg0OSAyODAgODU5 Debt|MTcgMjg2IDg0OSAzMTQgODU5 at|MTcgMzE4IDg1MSAzMjggODU5 risk|MTcgMzMzIDg0OSAzNTMgODU5 is|MTcgMzU4IDg1MiAzNjcgODU5 debt|MTcgMzcxIDg0OSAzOTcgODU5 of|MTcgMzk3IDg0MCA0MTAgODY5 firms|MTcgNDE0IDg0MCA0NDQgODY5 with|MTcgNDQzIDg0MCA0NzAgODY5 ratio|MTcgNDc3IDg0OSA1NzMgODYy of|MTcgNTAzIDg0MCA1MTkgODY5 eamings|MTcgNTIwIDg0OSA1NzIgODYy before|MTcgNTc3IDg0OSA2MTUgODU5 interest,|MTcgNjE5IDg1MCA2NjYgODYw tax.|MTcgNjcxIDg1MSA2OTIgODYw depreciation,|MTcgNjk3IDg0OSA3NzMgODYx and|MTcgNzc3IDg0OSA3OTkgODU5 amortization|MTcgODA0IDg1MCA4NzYgODU5 to|MTcgODgwIDg1MCA4OTIgODU5 interest|MTcgODk2IDg1MSA5NDAgODU5 expense|MTcgOTQ0IDg1MiA5OTQgODYx less|MTcgOTk5IDg0OSAxMDIyIDg1OQ== than|MTcgMTAyNiA4NDkgMTA1MiA4NTk= 2.|MTcgMTA1NyA4NDkgMTA2MyA4NTk= GDP|MTcgMTA3MiA4NDkgMTEwMCA4NTk= is|MTcgMTEwNSA4NTIgMTExNCA4NTk= gross|MTcgMTExOCA4NTIgMTE1MCA4NjI= domestic|MTcgMjM0IDg2NCAyODggODc0 product|MTcgMjkyIDg2NCAzNDAgODc2 Emerging|MTcgMjU5IDg3OSAzMTUgODky market|MTcgMzIwIDg3OSAzNjEgODg5 economies|MTcgMzY1IDg4MiA0MjkgODg5 (EME)|MTcgNDM0IDg3OSA0NzIgODkx include|MTcgNDc2IDg3OSA1MTggODg5 Argentina,|MTcgNTIyIDg3OSA1ODMgODky Brazil.|MTcgNTg4IDg3OSA2MjQgODkw Chile,|MTcgNjI5IDg3OSA2NjIgODkw China|MTcgNjY3IDg3OSA3MDEgODg5 (including|MTcgNzA2IDg3OSA3NjMgODky Hong|MTcgNzY4IDg3OSA3OTkgODky Kong),|MTcgODA0IDg3OSA4NDIgODky Hungary.|MTcgODQ3IDg3OSA5MDEgODky India,|MTcgOTA2IDg3OSA5MzcgODkw Indonesia,|MTcgOTQzIDg3OSAxMDA0IDg5MA== Malaysia,|MTcgMTAwOSA4NzkgMTA2NCA4OTI= Mexico,|MTcgMTA2OSA4NzkgMTExNSA4OTA= Poland,|MTcgMTEyMCA4NzkgMTE2NCA4OTA= Russia,|MTcgMjM0IDg5NCAyNzggOTA1 South|MTcgMjgzIDg5NCAzMTcgOTA0 Africa,|MTcgMzIyIDg5NCAzNTkgOTA1 South|MTcgMzY0IDg5NCAzOTkgOTA0 Korea,|MTcgNDAzIDg5NCA0NDEgOTA1 Thailand,|MTcgNDQ2IDg5NCA1MDEgOTA1 and|MTcgNTA2IDg5NCA1MjggOTA0 Turkey.|MTcgNTMyIDg5NCA1NzYgOTA3 **|MTcgMjUwIDkwOSAyNTggOTEz Asian|MTcgMjYzIDkwOSAyOTYgOTE5 financial|MTcgMzAxIDkwOSAzNTAgOTE5 crisis|MTcgMzU0IDkxMiAzODQgOTE5 is|MTcgMzg5IDkwOSAzOTggOTE5 GDP-weighted|MTcgNDAzIDkwOSA0ODkgOTIy average|MTcgNDk0IDkxMiA1NDIgOTIy of|MTcgNTQzIDkwMCA1NTggOTI5 Hong|MTcgNTYxIDkwOSA1OTMgOTIy Kong.|MTcgNTk3IDkwOSA2MzEgOTIy Singapore,|MTcgNjM3IDkwOSA3MDAgOTIy South|MTcgNzA1IDkwOSA3NDAgOTE5 Korea,|MTcgNzQ1IDkwOSA3ODMgOTIw and|MTcgNzg4IDkwOSA4MTAgOTE5 Thailand|MTcgODE0IDkwOSA4NjUgOTE5 in|MTcgODcwIDkxMiA4NzkgOTE5 1996.|MTcgODg2IDkwOSA5MTMgOTE5 ‘Source:|MTcgMjQ5IDkyNCAyOTUgOTM0 Bank|MTcgMzAwIDkyNCAzMjkgOTM0 for|MTcgMzM0IDkyNCAzNTAgOTM0 Intemational|MTcgMzU0IDkyNSA0MjcgOTM0 Settlements;|MTcgNDMyIDkyNCA1MDUgOTM1 Standard|MTcgNTExIDkyNCA1NjQgOTM0 &|MTcgNTY5IDkyNCA1NzcgOTM0 Poor's|MTcgNTgyIDkyNCA2MTkgOTM0 Global|MTcgNjI0IDkyNCA2NjIgOTM0 Market|MTcgNjY3IDkyNCA3MDcgOTM0 Intelligence;|MTcgNzEyIDkyNCA3ODIgOTM3 Federal|MTcgNzg4IDkyNCA4MzIgOTM0 Reserve|MTcgODM3IDkyNCA4ODYgOTM0 Board|MTcgODkxIDkyNCA5MjYgOTM0 staff|MTcgOTMxIDkyNCA5NTYgOTM0 estimates,|MTcgOTYwIDkyNSAxMDE3IDkzNA== |MTcgMCAxMDIwIDE0NDAgMTA4MA== f|MTcgNDc5IDEwNDQgNDkwIDEwNjM= Governors|MTcgNDk1IDEwNDQgNjA4IDEwNjQ= of|MTcgNjIwIDEwNDQgNjQ1IDEwNjQ= the|MTcgNjUwIDEwNDQgNjgzIDEwNjQ= Federal|MTcgNjkyIDEwNDQgNzcyIDEwNjQ= R|MTcgNzg0IDEwNDUgNzk5IDEwNjM= ",
  "document_type": null
}
